source_zendesk_chat/__init__.py
source_zendesk_chat/components/bans_record_extractor.py
source_zendesk_chat/manifest.yaml
source_zendesk_chat/run.py
source_zendesk_chat/schemas/accounts.json
source_zendesk_chat/schemas/agent_timeline.json
source_zendesk_chat/schemas/agents.json
source_zendesk_chat/schemas/bans.json
source_zendesk_chat/schemas/chats.json
source_zendesk_chat/schemas/departments.json
source_zendesk_chat/schemas/goals.json
source_zendesk_chat/schemas/roles.json
source_zendesk_chat/schemas/routing_settings.json
source_zendesk_chat/schemas/shortcuts.json
source_zendesk_chat/schemas/skills.json
source_zendesk_chat/schemas/triggers.json
source_zendesk_chat/schemas/visitors.json
source_zendesk_chat/source.py
source_zendesk_chat/spec.json
airbyte_source_zendesk_chat-1.1.1.dist-info/METADATA
airbyte_source_zendesk_chat-1.1.1.dist-info/WHEEL
airbyte_source_zendesk_chat-1.1.1.dist-info/entry_points.txt
airbyte_source_zendesk_chat-1.1.1.dist-info/RECORD
